photofs/__init__.py
photofs/__main__.py
photofs/_cache.py
photofs/_http.py
photofs/_image.py
photofs/_source.py
photofs/_tag.py
photofs/_util.py
photofs/sources/__init__.py
photofs/sources/shotwell.py
photofs-1.3.data/scripts/photofs
photofs-1.3.dist-info/DESCRIPTION.rst
photofs-1.3.dist-info/METADATA
photofs-1.3.dist-info/RECORD
photofs-1.3.dist-info/WHEEL
photofs-1.3.dist-info/metadata.json
photofs-1.3.dist-info/pbr.json
photofs-1.3.dist-info/top_level.txt
photofs-1.3.dist-info/zip-safe
