Metadata-Version: 2.0
Name: photofs
Version: 1.3
Summary: Explore tagged photos from Shotwell in the filesystem
Home-page: https://github.com/moses-palmer/photofs
Author: Moses Palmér
Author-email: moses.palmer@gmail.com
License: GPLv3
Platform: UNKNOWN
Requires-Dist: fusepy (>=2.0.2)
